pyselenium_localstorage/__init__.py
pyselenium_localstorage/codes.py
pyselenium_localstorage/local_storage.py
pyselenium_localstorage-0.1.1.dist-info/METADATA
pyselenium_localstorage-0.1.1.dist-info/WHEEL
pyselenium_localstorage-0.1.1.dist-info/top_level.txt
pyselenium_localstorage-0.1.1.dist-info/zip-safe
pyselenium_localstorage-0.1.1.dist-info/RECORD
