Metadata-Version: 2.1
Name: pyselenium-localstorage
Version: 0.1.1
Summary: pythonic selenium proxy for browser local storage
Home-page: https://github.com/mrafee113/pyselenium_localstorage
